Tokyocovidage.py
japantokyocovidage-0.0.2.dist-info/METADATA
japantokyocovidage-0.0.2.dist-info/WHEEL
japantokyocovidage-0.0.2.dist-info/entry_points.txt
japantokyocovidage-0.0.2.dist-info/top_level.txt
japantokyocovidage-0.0.2.dist-info/RECORD
