Metadata-Version: 2.1
Name: japantokyocovidage
Version: 0.0.2
Summary: A package for visualization of aggregate data of players in "tokyocovidage"
Home-page: https://github.com/s2022071/japantokyocovidage
Author: taiki shirato
Author-email: taikishirato4869@gmail.com
License: UNKNOWN
Project-URL: Bug Tracker, https://github.com/s2022071/japantokyocovidage
Platform: UNKNOWN
Classifier: Programming Language :: Python :: 3
Classifier: License :: OSI Approved :: MIT License
Classifier: Operating System :: OS Independent
Requires-Python: >=3.7
